mlmc/__init__.py
mlmc/_version.py
mlmc/save_and_load.py
mlmc/data/SingleLabelDataset.py
mlmc/data/__init__.py
mlmc/data/data_loaders.py
mlmc/data/data_loaders_text.py
mlmc/data/sampler.py
mlmc/data/transformer.py
mlmc/graph/__init__.py
mlmc/graph/embeddings.py
mlmc/graph/graph_loaders.py
mlmc/graph/graph_operations.py
mlmc/graph/helpers.py
mlmc/layers/__init__.py
mlmc/layers/label_layers.py
mlmc/layers/lstm.py
mlmc/layers/metric_layers.py
mlmc/layers/mogrifier.py
mlmc/layers/probability.py
mlmc/layers/weighted_aggregation.py
mlmc/loss/__init__.py
mlmc/loss/smoothing_loss.py
mlmc/metrics/__init__.py
mlmc/metrics/multilabel.py
mlmc/metrics/precisionk.py
mlmc/models/KimCNN.py
mlmc/models/LSAN.py
mlmc/models/LSANOriginalTransformer.py
mlmc/models/LSANOriginalTransformerNoClasses.py
mlmc/models/SKG_ML.py
mlmc/models/XMLCNN.py
mlmc/models/ZAGCNN.py
mlmc/models/ZAGCNNLM.py
mlmc/models/__init__.py
mlmc/models/abstracts.py
mlmc/models/abstracts_lm.py
mlmc/models/lm_mogrifier.py
mlmc/representation/__init__.py
mlmc/representation/character.py
mlmc/representation/custom_embedding.txt
mlmc/representation/embedder.py
mlmc/representation/label_embeddings.py
mlmc/representation/labels.py
mlmc/representation/model.txt
mlmc/representation/output_transformations.py
mlmc/representation/postprocessing_vectors.py
mlmc/representation/representations.py
mlmc/representation/similarities.py
melmac-76693.dist-info/METADATA
melmac-76693.dist-info/WHEEL
melmac-76693.dist-info/top_level.txt
melmac-76693.dist-info/RECORD
