Metadata-Version: 2.1
Name: melmac
Version: 76693
Summary: A package for neural multilabel and multiclass classification.
Home-page: UNKNOWN
Author: Janos Borst
Author-email: borst@informatik.uni-leipzig.de
License: UNKNOWN
Platform: UNKNOWN
Requires-Python: >=3.6
Requires-Dist: numpy
Requires-Dist: transformers
Requires-Dist: nltk
Requires-Dist: node2vec
Requires-Dist: scikit-learn
Requires-Dist: pytorch-ignite
Requires-Dist: tqdm
Requires-Dist: networkx
Requires-Dist: bs4
Requires-Dist: pytest
Requires-Dist: pytest-cov
Requires-Dist: rdflib
Requires-Dist: h5py
